courts_db/__init__.py
courts_db/text_utils.py
courts_db/utils.py
courts_db/data/courts.json
courts_db/data/states.json
courts_db/data/variables.json
courts_db/data/places/al_counties.txt
courts_db/data/places/al_districts.txt
courts_db/data/places/al_municipals.txt
courts_db/data/places/al_probates.txt
courts_db/data/places/ar_circuits.txt
courts_db/data/places/ar_cities.txt
courts_db/data/places/ar_districts.txt
courts_db/data/places/az_cities.txt
courts_db/data/places/az_superior_cts.txt
courts_db/data/places/ca_counties.txt
courts_db/data/places/co_counties.txt
courts_db/data/places/co_munis.txt
courts_db/data/places/ct_superior.txt
courts_db/data/places/fl_counties.txt
courts_db/data/places/ga_juvenile.txt
courts_db/data/places/ga_magistrates.txt
courts_db/data/places/ga_probates.txt
courts_db/data/places/ga_state_ct.txt
courts_db/data/places/gand_divisions.txt
courts_db/data/places/md_circuits.txt
courts_db/data/places/nj_counties.txt
courts_db/data/places/ny_cities.txt
courts_db/data/places/ny_counties.txt
courts_db/data/places/ny_towns.txt
courts_db/data/places/oh_counties.txt
courts_db/data/places/pa_places.txt
courts_db/data/places/va_circuits.txt
courts_db/data/places/va_cities.txt
courts_db-0.10.26.dist-info/licenses/LICENSE
courts_db-0.10.26.dist-info/METADATA
courts_db-0.10.26.dist-info/WHEEL
courts_db-0.10.26.dist-info/top_level.txt
courts_db-0.10.26.dist-info/RECORD
